easyBT/__init__.py
easyBT/binarysearchtree.py
easyBT/binarytree.py
easyBT/test_.py
easyBT/testing.py
easybt-0.0.9.dist-info/METADATA
easybt-0.0.9.dist-info/WHEEL
easybt-0.0.9.dist-info/top_level.txt
easybt-0.0.9.dist-info/RECORD
